CHANGES.txt
README.txt
ZopePublicLicense.txt
bootstrap.py
buildout.cfg
setup.py
src/zc/__init__.py
src/zc.i18n.egg-info/PKG-INFO
src/zc.i18n.egg-info/SOURCES.txt
src/zc.i18n.egg-info/dependency_links.txt
src/zc.i18n.egg-info/namespace_packages.txt
src/zc.i18n.egg-info/not-zip-safe
src/zc.i18n.egg-info/requires.txt
src/zc.i18n.egg-info/top_level.txt
src/zc/i18n/__init__.py
src/zc/i18n/configure.zcml
src/zc/i18n/date.py
src/zc/i18n/duration.py
src/zc/i18n/duration.txt
src/zc/i18n/i18n.py
src/zc/i18n/tests.py
src/zc/i18n/locales/README.txt
src/zc/i18n/locales/zc.i18n.pot
src/zc/i18n/locales/de/LC_MESSAGES/zc.i18n.mo
src/zc/i18n/locales/de/LC_MESSAGES/zc.i18n.po